trytond/modules/health_imaging/COPYING
trytond/modules/health_imaging/README.rst
trytond/modules/health_imaging/__init__.py
trytond/modules/health_imaging/data/gnuhealth_commands.xml
trytond/modules/health_imaging/data/health_imaging_sequences.xml
trytond/modules/health_imaging/data/imaging_data.xml
trytond/modules/health_imaging/health_imaging.py
trytond/modules/health_imaging/health_imaging_report.xml
trytond/modules/health_imaging/health_imaging_view.xml
trytond/modules/health_imaging/icons/execute_icon.svg
trytond/modules/health_imaging/icons/imaging_icon.svg
trytond/modules/health_imaging/locale/ar.po
trytond/modules/health_imaging/locale/de.po
trytond/modules/health_imaging/locale/el.po
trytond/modules/health_imaging/locale/eo.po
trytond/modules/health_imaging/locale/es.po
trytond/modules/health_imaging/locale/fr.po
trytond/modules/health_imaging/locale/health_imaging.pot
trytond/modules/health_imaging/locale/it_IT.po
trytond/modules/health_imaging/locale/ja_JP.po
trytond/modules/health_imaging/locale/ka.po
trytond/modules/health_imaging/locale/lo.po
trytond/modules/health_imaging/locale/pt_BR.po
trytond/modules/health_imaging/locale/sv.po
trytond/modules/health_imaging/locale/tr.po
trytond/modules/health_imaging/locale/uk.po
trytond/modules/health_imaging/locale/vi.po
trytond/modules/health_imaging/locale/zh_CN.po
trytond/modules/health_imaging/pyproject.toml
trytond/modules/health_imaging/report/imaging_study_report.fodt
trytond/modules/health_imaging/security/access_rights.xml
trytond/modules/health_imaging/sequences.py
trytond/modules/health_imaging/tests/__init__.py
trytond/modules/health_imaging/tests/test_health_imaging.py
trytond/modules/health_imaging/tryton.cfg
trytond/modules/health_imaging/view/imaging_test_form.xml
trytond/modules/health_imaging/view/imaging_test_request_form.xml
trytond/modules/health_imaging/view/imaging_test_request_tree.xml
trytond/modules/health_imaging/view/imaging_test_result_form.xml
gnuhealth_imaging-5.0.2.dist-info/METADATA
gnuhealth_imaging-5.0.2.dist-info/WHEEL
gnuhealth_imaging-5.0.2.dist-info/licenses/COPYING
gnuhealth_imaging-5.0.2.dist-info/RECORD
